impulsare_distributer
