Metadata-Version: 1.1
Name: impulsare-distributer
Version: 1.0b4
Summary: A distributer that helps to publish to a queue and process tasks from a queue
Home-page: https://github.com/impulsare/distributer
Author: Emmanuel Dyan
Author-email: emmanuel@impulsare.io
License: AGPLv3
Download-URL: https://github.com/impulsare/distributer/tarball/1.0b4
Keywords: distributer,python,redis,impulsare,rq,esb,etl
Platform: UNKNOWN
Classifier: Development Status :: 4 - Beta
Classifier: Intended Audience :: Developers
Classifier: Intended Audience :: Information Technology
Classifier: Intended Audience :: Science/Research
Classifier: Intended Audience :: System Administrators
Classifier: License :: OSI Approved :: GNU Affero General Public License v3 or later (AGPLv3+)
Classifier: Programming Language :: Python :: 3.3
Classifier: Programming Language :: Python :: 3.4
Classifier: Programming Language :: Python :: 3.5
Classifier: Programming Language :: Python :: 3.6
Classifier: Topic :: Scientific/Engineering
Classifier: Topic :: System :: Distributed Computing
Classifier: Topic :: System :: Systems Administration
